webtoons-0.1.2.dist-info/RECORD
webtoons-0.1.2.dist-info/WHEEL
webtoons-0.1.2.dist-info/METADATA
webtoons-0.1.2.dist-info/top_level.txt
webtoons-0.1.2.dist-info/DESCRIPTION.rst
webtoons-0.1.2.dist-info/metadata.json
webtoons/__init__.py
