Metadata-Version: 2.0
Name: webtoons
Version: 0.1.2
Summary: A small package for getting Webtoon comics for Python3.
Home-page: https://github.com/joshdabosh/webtoons
Author: Joshua Wang
Author-email: jwanggt@gmail.com
License: UNKNOWN
Platform: UNKNOWN
Classifier: Programming Language :: Python :: 3
Classifier: License :: OSI Approved :: MIT License
Classifier: Operating System :: OS Independent
Requires-Dist: bs4
Requires-Dist: requests
